monmoteur/__init__.py
monmoteur/build.py
monmoteur/setup.py
monmoteur/dll/SDL2.dll
monmoteur/dll/SDL2_image.dll
monmoteur/dll/SDL2_mixer.dll
monmoteur/dll/jeu.dll
monmoteur-0.1.3.dist-info/METADATA
monmoteur-0.1.3.dist-info/WHEEL
monmoteur-0.1.3.dist-info/top_level.txt
monmoteur-0.1.3.dist-info/RECORD
