Metadata-Version: 2.4
Name: monmoteur
Version: 0.1.3
Summary: Un petit moteur de jeu en C avec bindings Python
Author-email: Baptiste GUERIN <baptiste.guerin34@gmail.com>
Requires-Python: >=3.9
